upsilon_py/__init__.py
upsilon_py/__main__.py
upsilon_py/main.js
upsilon_py-1.0.1.dist-info/METADATA
upsilon_py-1.0.1.dist-info/WHEEL
upsilon_py-1.0.1.dist-info/RECORD
