Metadata-Version: 2.1
Name: upsilon-py
Version: 1.0.1
Summary: Connect to NumWorks calculators using Python
Author: Yaya-Cout
Author-email: yaya.cout@free.fr
Requires-Python: >=3.10,<4.0
Classifier: Programming Language :: Python :: 3
Classifier: Programming Language :: Python :: 3.10
Classifier: Programming Language :: Python :: 3.11
